{
  "status": "success",
  "lat": 23.53232,
  "lon": 87.34411,
  "forecast_data": {
    "station_0": [
      {
        "time": "06:30 PM",
        "aqi": 105.36,
        "health_info": {
          "category": "Moderate",
          "color": "#FF7E00"
        }
      },
      {
        "time": "07:30 PM",
        "aqi": 104.33,
        "health_info": {
          "category": "Moderate",
          "color": "#FF7E00"
        }
      },
      {
        "time": "08:30 PM",
        "aqi": 104.41,
        "health_info": {
          "category": "Moderate",
          "color": "#FF7E00"
        }
      },
      {
        "time": "09:30 PM",
        "aqi": 104.44,
        "health_info": {
          "category": "Moderate",
          "color": "#FF7E00"
        }
      },
      {
        "time": "10:30 PM",
        "aqi": 105.32,
        "health_info": {
          "category": "Moderate",
          "color": "#FF7E00"
        }
      },
      {
        "time": "11:30 PM",
        "aqi": 104.63,
        "health_info": {
          "category": "Moderate",
          "color": "#FF7E00"
        }
      },
      {
        "time": "12:30 AM",
        "aqi": 103.7,
        "health_info": {
          "category": "Moderate",
          "color": "#FF7E00"
        }
      },
      {
        "time": "01:30 AM",
        "aqi": 103.79,
        "health_info": {
          "category": "Moderate",
          "color": "#FF7E00"
        }
      },
      {
        "time": "02:30 AM",
        "aqi": 107.13,
        "health_info": {
          "category": "Moderate",
          "color": "#FF7E00"
        }
      },
      {
        "time": "03:30 AM",
        "aqi": 113.29,
        "health_info": {
          "category": "Moderate",
          "color": "#FF7E00"
        }
      },
      {
        "time": "04:30 AM",
        "aqi": 120.89,
        "health_info": {
          "category": "Moderate",
          "color": "#FF7E00"
        }
      },
      {
        "time": "05:30 AM",
        "aqi": 130.27,
        "health_info": {
          "category": "Moderate",
          "color": "#FF7E00"
        }
      }
    ],
    "station_1": [
      {
        "time": "06:30 PM",
        "aqi": 105.46,
        "health_info": {
          "category": "Moderate",
          "color": "#FF7E00"
        }
      },
      {
        "time": "07:30 PM",
        "aqi": 104.39,
        "health_info": {
          "category": "Moderate",
          "color": "#FF7E00"
        }
      },
      {
        "time": "08:30 PM",
        "aqi": 104.45,
        "health_info": {
          "category": "Moderate",
          "color": "#FF7E00"
        }
      },
      {
        "time": "09:30 PM",
        "aqi": 104.45,
        "health_info": {
          "category": "Moderate",
          "color": "#FF7E00"
        }
      },
      {
        "time": "10:30 PM",
        "aqi": 105.35,
        "health_info": {
          "category": "Moderate",
          "color": "#FF7E00"
        }
      },
      {
        "time": "11:30 PM",
        "aqi": 104.72,
        "health_info": {
          "category": "Moderate",
          "color": "#FF7E00"
        }
      },
      {
        "time": "12:30 AM",
        "aqi": 103.88,
        "health_info": {
          "category": "Moderate",
          "color": "#FF7E00"
        }
      },
      {
        "time": "01:30 AM",
        "aqi": 104.06,
        "health_info": {
          "category": "Moderate",
          "color": "#FF7E00"
        }
      },
      {
        "time": "02:30 AM",
        "aqi": 107.49,
        "health_info": {
          "category": "Moderate",
          "color": "#FF7E00"
        }
      },
      {
        "time": "03:30 AM",
        "aqi": 113.7,
        "health_info": {
          "category": "Moderate",
          "color": "#FF7E00"
        }
      },
      {
        "time": "04:30 AM",
        "aqi": 121.32,
        "health_info": {
          "category": "Moderate",
          "color": "#FF7E00"
        }
      },
      {
        "time": "05:30 AM",
        "aqi": 130.68,
        "health_info": {
          "category": "Moderate",
          "color": "#FF7E00"
        }
      }
    ],
    "station_2": [
      {
        "time": "06:30 PM",
        "aqi": 105.42,
        "health_info": {
          "category": "Moderate",
          "color": "#FF7E00"
        }
      },
      {
        "time": "07:30 PM",
        "aqi": 104.37,
        "health_info": {
          "category": "Moderate",
          "color": "#FF7E00"
        }
      },
      {
        "time": "08:30 PM",
        "aqi": 104.44,
        "health_info": {
          "category": "Moderate",
          "color": "#FF7E00"
        }
      },
      {
        "time": "09:30 PM",
        "aqi": 104.45,
        "health_info": {
          "category": "Moderate",
          "color": "#FF7E00"
        }
      },
      {
        "time": "10:30 PM",
        "aqi": 105.33,
        "health_info": {
          "category": "Moderate",
          "color": "#FF7E00"
        }
      },
      {
        "time": "11:30 PM",
        "aqi": 104.68,
        "health_info": {
          "category": "Moderate",
          "color": "#FF7E00"
        }
      },
      {
        "time": "12:30 AM",
        "aqi": 103.8,
        "health_info": {
          "category": "Moderate",
          "color": "#FF7E00"
        }
      },
      {
        "time": "01:30 AM",
        "aqi": 103.95,
        "health_info": {
          "category": "Moderate",
          "color": "#FF7E00"
        }
      },
      {
        "time": "02:30 AM",
        "aqi": 107.35,
        "health_info": {
          "category": "Moderate",
          "color": "#FF7E00"
        }
      },
      {
        "time": "03:30 AM",
        "aqi": 113.53,
        "health_info": {
          "category": "Moderate",
          "color": "#FF7E00"
        }
      },
      {
        "time": "04:30 AM",
        "aqi": 121.15,
        "health_info": {
          "category": "Moderate",
          "color": "#FF7E00"
        }
      },
      {
        "time": "05:30 AM",
        "aqi": 130.51,
        "health_info": {
          "category": "Moderate",
          "color": "#FF7E00"
        }
      }
    ],
    "station_3": [
      {
        "time": "06:30 PM",
        "aqi": 105.49,
        "health_info": {
          "category": "Moderate",
          "color": "#FF7E00"
        }
      },
      {
        "time": "07:30 PM",
        "aqi": 104.4,
        "health_info": {
          "category": "Moderate",
          "color": "#FF7E00"
        }
      },
      {
        "time": "08:30 PM",
        "aqi": 104.44,
        "health_info": {
          "category": "Moderate",
          "color": "#FF7E00"
        }
      },
      {
        "time": "09:30 PM",
        "aqi": 104.43,
        "health_info": {
          "category": "Moderate",
          "color": "#FF7E00"
        }
      },
      {
        "time": "10:30 PM",
        "aqi": 105.31,
        "health_info": {
          "category": "Moderate",
          "color": "#FF7E00"
        }
      },
      {
        "time": "11:30 PM",
        "aqi": 104.65,
        "health_info": {
          "category": "Moderate",
          "color": "#FF7E00"
        }
      },
      {
        "time": "12:30 AM",
        "aqi": 103.75,
        "health_info": {
          "category": "Moderate",
          "color": "#FF7E00"
        }
      },
      {
        "time": "01:30 AM",
        "aqi": 103.85,
        "health_info": {
          "category": "Moderate",
          "color": "#FF7E00"
        }
      },
      {
        "time": "02:30 AM",
        "aqi": 107.18,
        "health_info": {
          "category": "Moderate",
          "color": "#FF7E00"
        }
      },
      {
        "time": "03:30 AM",
        "aqi": 113.3,
        "health_info": {
          "category": "Moderate",
          "color": "#FF7E00"
        }
      },
      {
        "time": "04:30 AM",
        "aqi": 120.86,
        "health_info": {
          "category": "Moderate",
          "color": "#FF7E00"
        }
      },
      {
        "time": "05:30 AM",
        "aqi": 130.2,
        "health_info": {
          "category": "Moderate",
          "color": "#FF7E00"
        }
      }
    ]
  },
  "meta": {
    "unit": "AQI",
    "history_ended_at": "2026-02-17 17:30:00",
    "forecast_start": "06:30 PM",
    "forecast_window": "12 hours"
  }
}